{
  "generatedAt": "2026-06-08T15:20:14.697Z",
  "sources": [
    {
      "id": "github-vercel-labs",
      "category": "github",
      "title": "vercel-labs GitHub",
      "organization": "vercel-labs",
      "sourceUrl": "https://github.com/vercel-labs",
      "apiUrl": "https://api.github.com/orgs/vercel-labs/repos?sort=updated&per_page=12",
      "limit": 12,
      "status": "ok",
      "fetchedAt": "2026-06-08T15:20:14.697Z",
      "items": [
        {
          "title": "vercel-labs/agent-skills",
          "link": "https://github.com/vercel-labs/agent-skills",
          "id": "1112540808",
          "publishedAt": "2026-06-03T17:03:05Z",
          "updatedAt": "2026-06-08T15:19:46Z",
          "author": "vercel-labs",
          "summary": "Vercel's official collection of agent skills",
          "stars": 27725,
          "forks": 2508,
          "language": "JavaScript",
          "openIssues": 151
        },
        {
          "title": "vercel-labs/skills",
          "link": "https://github.com/vercel-labs/skills",
          "id": "1134543109",
          "publishedAt": "2026-06-05T14:38:13Z",
          "updatedAt": "2026-06-08T15:18:53Z",
          "author": "vercel-labs",
          "summary": "The open agent skills tool - npx skills",
          "stars": 21696,
          "forks": 1738,
          "language": "TypeScript",
          "openIssues": 693
        },
        {
          "title": "vercel-labs/agent-browser",
          "link": "https://github.com/vercel-labs/agent-browser",
          "id": "1132001614",
          "publishedAt": "2026-06-05T19:17:51Z",
          "updatedAt": "2026-06-08T15:18:25Z",
          "author": "vercel-labs",
          "summary": "Browser automation CLI for AI agents",
          "stars": 35572,
          "forks": 2240,
          "language": "Rust",
          "openIssues": 512
        },
        {
          "title": "vercel-labs/just-bash",
          "link": "https://github.com/vercel-labs/just-bash",
          "id": "1121859126",
          "publishedAt": "2026-06-04T17:38:57Z",
          "updatedAt": "2026-06-08T15:18:10Z",
          "author": "vercel-labs",
          "summary": "Bash for Agents",
          "stars": 3705,
          "forks": 207,
          "language": "TypeScript",
          "openIssues": 71
        },
        {
          "title": "vercel-labs/json-render",
          "link": "https://github.com/vercel-labs/json-render",
          "id": "1134411737",
          "publishedAt": "2026-05-20T19:19:47Z",
          "updatedAt": "2026-06-08T15:15:52Z",
          "author": "vercel-labs",
          "summary": "The Generative UI framework",
          "stars": 15043,
          "forks": 813,
          "language": "TypeScript",
          "openIssues": 93
        },
        {
          "title": "vercel-labs/portless",
          "link": "https://github.com/vercel-labs/portless",
          "id": "1158537997",
          "publishedAt": "2026-06-04T20:57:47Z",
          "updatedAt": "2026-06-08T14:59:24Z",
          "author": "vercel-labs",
          "summary": "Replace port numbers with stable, named local URLs. For humans and agents.",
          "stars": 9677,
          "forks": 305,
          "language": "TypeScript",
          "openIssues": 103
        },
        {
          "title": "vercel-labs/open-agents",
          "link": "https://github.com/vercel-labs/open-agents",
          "id": "1123338559",
          "publishedAt": "2026-06-08T07:40:31Z",
          "updatedAt": "2026-06-08T14:54:39Z",
          "author": "vercel-labs",
          "summary": "An open source template for building cloud agents.",
          "stars": 5610,
          "forks": 731,
          "language": "TypeScript",
          "openIssues": 52
        },
        {
          "title": "vercel-labs/deepsec",
          "link": "https://github.com/vercel-labs/deepsec",
          "id": "1225774688",
          "publishedAt": "2026-05-30T17:03:39Z",
          "updatedAt": "2026-06-08T14:49:35Z",
          "author": "vercel-labs",
          "summary": "Deepsec is a security harness for finding vulnerabilities in your codebase powered by coding agents",
          "stars": 3118,
          "forks": 217,
          "language": "TypeScript",
          "openIssues": 30
        },
        {
          "title": "vercel-labs/coding-agent-template",
          "link": "https://github.com/vercel-labs/coding-agent-template",
          "id": "1062625887",
          "publishedAt": "2026-04-13T21:44:42Z",
          "updatedAt": "2026-06-08T14:22:53Z",
          "author": "vercel-labs",
          "summary": "Multi-agent AI coding platform powered by Vercel Sandbox and AI Gateway",
          "stars": 1726,
          "forks": 283,
          "language": "TypeScript",
          "openIssues": 14
        },
        {
          "title": "vercel-labs/ai-sdk-gateway-demo",
          "link": "https://github.com/vercel-labs/ai-sdk-gateway-demo",
          "id": "960108014",
          "publishedAt": "2026-01-17T20:09:08Z",
          "updatedAt": "2026-06-08T14:02:00Z",
          "author": "vercel-labs",
          "summary": "",
          "stars": 126,
          "forks": 44,
          "language": "TypeScript",
          "openIssues": 1
        },
        {
          "title": "vercel-labs/zero-native",
          "link": "https://github.com/vercel-labs/zero-native",
          "id": "1233290067",
          "publishedAt": "2026-05-13T16:47:35Z",
          "updatedAt": "2026-06-08T13:27:21Z",
          "author": "vercel-labs",
          "summary": "Build desktop + mobile apps with Zig and web UI",
          "stars": 4122,
          "forks": 172,
          "language": "Zig",
          "openIssues": 39
        },
        {
          "title": "vercel-labs/openclaw",
          "link": "https://github.com/vercel-labs/openclaw",
          "id": "1231415831",
          "publishedAt": "2026-05-22T18:38:53Z",
          "updatedAt": "2026-06-08T12:30:24Z",
          "author": "vercel-labs",
          "summary": "Your own personal AI assistant. Any OS. Any Platform. The lobster way. 🦞 ",
          "stars": 3,
          "forks": 0,
          "language": "TypeScript",
          "openIssues": 0
        }
      ]
    }
  ]
}
